jcecard/__init__.py
jcecard/apdu.py
jcecard/atr.py
jcecard/card_data.py
jcecard/crypto_backend.py
jcecard/main.py
jcecard/pin_manager.py
jcecard/security_state.py
jcecard/tcp_server.py
jcecard/tlv.py
jcecard/commands/__init__.py
jcecard/piv/__init__.py
jcecard/piv/applet.py
jcecard/piv/data_objects.py
jcecard-0.1.0.dist-info/entry_points.txt
jcecard-0.1.0.dist-info/licenses/LICENSE
jcecard-0.1.0.dist-info/WHEEL
jcecard-0.1.0.dist-info/METADATA
jcecard-0.1.0.dist-info/RECORD
