Metadata-Version: 2.4
Name: jcecard
Version: 0.1.0
Summary: A virtual OpenPGP smart card implementation using johnnycanencrypt
Keywords: openpgp,smartcard,virtual,cryptography
Author-email: Kushal Das <mail@kushaldas.in>
Requires-Python: >=3.10
Classifier: Development Status :: 3 - Alpha
Classifier: Intended Audience :: Developers
Classifier: License :: OSI Approved :: BSD License
Classifier: Operating System :: POSIX :: Linux
Classifier: Programming Language :: Python :: 3
Classifier: Programming Language :: Python :: 3.10
Classifier: Programming Language :: Python :: 3.11
Classifier: Programming Language :: Python :: 3.12
Classifier: Programming Language :: Python :: 3.13
Classifier: Programming Language :: Python :: 3.14
Classifier: Topic :: Security :: Cryptography
Classifier: Topic :: Software Development :: Libraries :: Python Modules
License-File: LICENSE
Requires-Dist: johnnycanencrypt>=0.17.0
Requires-Dist: cryptography
Requires-Dist: pytest>=7.0 ; extra == "dev"
Requires-Dist: pytest-cov ; extra == "dev"
Requires-Dist: flit ; extra == "dev"
Requires-Dist: ty ; extra == "dev"
Requires-Dist: pyscard ; extra == "dev"
Requires-Dist: ruff ; extra == "dev"
Requires-Dist: pexpect ; extra == "dev"
Project-URL: Documentation, https://github.com/kushaldas/jcecard
Project-URL: Homepage, https://github.com/kushaldas/jcecard
Project-URL: Issues, https://github.com/kushaldas/jcecard/issues
Project-URL: Repository, https://github.com/kushaldas/jcecard
Provides-Extra: dev
